.pylintrc
.travis.yml
AUTHORS
ChangeLog
LICENSE
README.md
requirements.txt
setup.cfg
setup.py
tests/__init__.py
tests/conftest.py
tests/test_woof.py
woof/README.md
woof/__init__.py
woof/entry_points.py
woof/woof.py
woof.egg-info/PKG-INFO
woof.egg-info/SOURCES.txt
woof.egg-info/dependency_links.txt
woof.egg-info/entry_points.txt
woof.egg-info/not-zip-safe
woof.egg-info/pbr.json
woof.egg-info/requires.txt
woof.egg-info/top_level.txt
woof/backends/__init__.py
woof/backends/base.py
woof/backends/telegram_backend.py