Metadata-Version: 2.1
Name: woof
Version: 0.0.3
Summary: A simple utility library for adding flexible notifications to Python scripts
Home-page: https://github.com/vmalloc/cob
Author: Rotem Yaari
Author-email: vmalloc@gmail.com
License: MIT
Platform: UNKNOWN
Classifier: Environment :: Console
Classifier: Intended Audience :: Developers
Classifier: Operating System :: OS Independent
Classifier: Programming Language :: Python
Provides-Extra: testing
